surfaice_assistant/abstract_provider/__init__.py
surfaice_assistant/abstract_provider/assistant.py
surfaice_assistant/implementations/__init__.py
surfaice_assistant/implementations/openai_provider.py
surfaice_assistant/processor.py
surfaice_assistant/processor_2.py
surfaice_assistant/py.typed
surfaice_assistant-0.3.5.dist-info/METADATA
surfaice_assistant-0.3.5.dist-info/WHEEL
surfaice_assistant-0.3.5.dist-info/RECORD
